<?xml version="1.0" encoding="utf-8"?>
<MusicData xmlns:xsi="http://www.w3.org/2001/XMLSchema-instance" xmlns:xsd="http://www.w3.org/2001/XMLSchema">
  <dataName>music011735</dataName>
  <netOpenName>
    <id>250924</id>
    <str>Net250924</str>
  </netOpenName>
  <releaseTagName>
    <id>4501</id>
    <str>Ver1.45.00</str>
  </releaseTagName>
  <disable>false</disable>
  <name>
    <id>11735</id>
    <str>ザムザ</str>
  </name>
  <rightsInfoName>
    <id>206</id>
    <str>©teniwoha</str>
  </rightsInfoName>
  <sortName>サムサ</sortName>
  <artistName>
    <id>284</id>
    <str>てにをは</str>
  </artistName>
  <genreName>
    <id>102</id>
    <str>niconicoボーカロイド</str>
  </genreName>
  <bpm>121</bpm>
  <version>25003</version>
  <AddVersion>
    <id>23</id>
    <str>PRiSM</str>
  </AddVersion>
  <movieName>
    <id>1735</id>
    <str>ザムザ</str>
  </movieName>
  <cueName>
    <id>1735</id>
    <str>ザムザ</str>
  </cueName>
  <dresscode>false</dresscode>
  <eventName>
    <id>25092421</id>
    <str>250924_02_1：通常楽曲（5曲）《新人類、ザムザ、バカ通信、ライアーダンサー、INFiNiTE ENERZY -Overdoze-》</str>
  </eventName>
  <eventName2>
    <id>0</id>
    <str>解放なし</str>
  </eventName2>
  <subEventName>
    <id>0</id>
    <str>解放なし</str>
  </subEventName>
  <lockType>0</lockType>
  <subLockType>1</subLockType>
  <dotNetListView>true</dotNetListView>
  <notesData>
    <Notes>
      <file>
        <path>011735_00.ma2</path>
      </file>
      <level>1</level>
      <levelDecimal>0</levelDecimal>
      <notesDesigner>
        <id>999</id>
        <str>-</str>
      </notesDesigner>
      <notesType>0</notesType>
      <musicLevelID>1</musicLevelID>
      <maxNotes>111</maxNotes>
      <isEnable>true</isEnable>
    </Notes>
    <Notes>
      <file>
        <path>011735_01.ma2</path>
      </file>
      <level>6</level>
      <levelDecimal>5</levelDecimal>
      <notesDesigner>
        <id>999</id>
        <str>-</str>
      </notesDesigner>
      <notesType>0</notesType>
      <musicLevelID>6</musicLevelID>
      <maxNotes>238</maxNotes>
      <isEnable>true</isEnable>
    </Notes>
    <Notes>
      <file>
        <path>011735_02.ma2</path>
      </file>
      <level>9</level>
      <levelDecimal>8</levelDecimal>
      <notesDesigner>
        <id>151</id>
        <str>まぐランド</str>
      </notesDesigner>
      <notesType>0</notesType>
      <musicLevelID>12</musicLevelID>
      <maxNotes>359</maxNotes>
      <isEnable>true</isEnable>
    </Notes>
    <Notes>
      <file>
        <path>011735_03.ma2</path>
      </file>
      <level>12</level>
      <levelDecimal>9</levelDecimal>
      <notesDesigner>
        <id>152</id>
        <str>Jack&amp;アマリリス</str>
      </notesDesigner>
      <notesType>0</notesType>
      <musicLevelID>18</musicLevelID>
      <maxNotes>634</maxNotes>
      <isEnable>true</isEnable>
    </Notes>
    <Notes>
      <file>
        <path>011735_04.ma2</path>
      </file>
      <level>0</level>
      <levelDecimal>0</levelDecimal>
      <notesDesigner>
        <id>0</id>
        <str />
      </notesDesigner>
      <notesType>0</notesType>
      <musicLevelID>0</musicLevelID>
      <maxNotes>0</maxNotes>
      <isEnable>false</isEnable>
    </Notes>
    <Notes>
      <file>
        <path>011735_05.ma2</path>
      </file>
      <level>0</level>
      <levelDecimal>0</levelDecimal>
      <notesDesigner>
        <id>0</id>
        <str />
      </notesDesigner>
      <notesType>0</notesType>
      <musicLevelID>0</musicLevelID>
      <maxNotes>0</maxNotes>
      <isEnable>false</isEnable>
    </Notes>
  </notesData>
  <utageKanjiName />
  <comment />
  <utagePlayStyle>0</utagePlayStyle>
  <fixedOptions>
    <FixedOption>
      <_fixedOptionName />
      <_fixedOptionValue />
    </FixedOption>
    <FixedOption>
      <_fixedOptionName />
      <_fixedOptionValue />
    </FixedOption>
    <FixedOption>
      <_fixedOptionName />
      <_fixedOptionValue />
    </FixedOption>
    <FixedOption>
      <_fixedOptionName />
      <_fixedOptionValue />
    </FixedOption>
  </fixedOptions>
  <jacketFile />
  <thumbnailName />
  <rightFile />
  <priority>0</priority>
</MusicData>